OWN_THE_PLANET_BOARD_GAME_EDITION/OwnThePlanetBoardGameEdition.py
OWN_THE_PLANET_BOARD_GAME_EDITION-1.dist-info/LICENSE
OWN_THE_PLANET_BOARD_GAME_EDITION-1.dist-info/METADATA
OWN_THE_PLANET_BOARD_GAME_EDITION-1.dist-info/WHEEL
OWN_THE_PLANET_BOARD_GAME_EDITION-1.dist-info/entry_points.txt
OWN_THE_PLANET_BOARD_GAME_EDITION-1.dist-info/top_level.txt
OWN_THE_PLANET_BOARD_GAME_EDITION-1.dist-info/RECORD
