Metadata-Version: 2.1
Name: OWN-THE-PLANET-BOARD-GAME-EDITION
Version: 1
Summary: This package contains implementation of the game "Own The Planet - Board Game Edition". The game involves the player and CPU competing to be the richest in the planet.
Home-page: https://github.com/DigitalCreativeApkDev/OWN_THE_PLANET_BOARD_GAME_EDITION
Author: DigitalCreativeApkDev
Author-email: digitalcreativeapkdev2022@gmail.com
License: MIT
Platform: UNKNOWN
Classifier: Programming Language :: Python :: 3
Classifier: Programming Language :: Python :: 3.7
